<?xml version="1.0" encoding="UTF-8"?>
<!-- Created with TexturePacker http://www.codeandweb.com/texturepacker-->
<!-- $TexturePacker:SmartUpdate:27a3f02e82506aa561dd4b0e032fbf3f:1/1$ -->
<TextureAtlas imagePath="TilesetWorld4.png">
    <SubTexture name="Mundo_04_Tile__0000_-" x="1" y="1" width="64" height="64"/>
    <SubTexture name="Mundo_04_Tile__0001_-" x="67" y="1" width="64" height="64"/>
    <SubTexture name="Mundo_04_Tile__0002_-" x="133" y="1" width="64" height="64"/>
    <SubTexture name="Mundo_04_Tile__0003_-" x="199" y="1" width="64" height="64"/>
    <SubTexture name="Mundo_04_Tile__0004_-" x="265" y="1" width="64" height="64"/>
    <SubTexture name="Mundo_04_Tile__0005_-" x="331" y="1" width="64" height="64"/>
    <SubTexture name="Mundo_04_Tile__0006_-" x="397" y="1" width="64" height="64"/>
    <SubTexture name="Mundo_04_Tile__0007_-" x="463" y="1" width="64" height="64"/>
    <SubTexture name="Mundo_04_Tile__0008_-" x="529" y="1" width="64" height="64"/>
    <SubTexture name="Mundo_04_Tile__0009_-" x="595" y="1" width="64" height="64"/>
    <SubTexture name="Mundo_04_Tile__0010_-" x="661" y="1" width="64" height="64"/>
    <SubTexture name="Mundo_04_Tile__0011_-" x="727" y="1" width="64" height="64"/>
    <SubTexture name="Mundo_04_Tile__0012_-" x="793" y="1" width="64" height="64"/>
    <SubTexture name="Mundo_04_Tile__0013_-" x="859" y="1" width="64" height="64"/>
    <SubTexture name="Mundo_04_Tile__0014_-" x="925" y="1" width="64" height="64"/>
    <SubTexture name="Mundo_04_Tile__0015_-" x="1" y="67" width="64" height="64"/>
    <SubTexture name="Mundo_04_Tile__0016_-" x="67" y="67" width="64" height="64"/>
    <SubTexture name="Mundo_04_Tile__0017_-" x="133" y="67" width="64" height="64"/>
    <SubTexture name="Mundo_04_Tile__0018_-" x="199" y="67" width="64" height="64"/>
    <SubTexture name="Mundo_04_Tile__0019_-" x="265" y="67" width="64" height="64"/>
    <SubTexture name="Mundo_04_Tile__0020_-" x="331" y="67" width="64" height="64"/>
    <SubTexture name="Mundo_04_Tile__0021_-" x="397" y="67" width="64" height="64"/>
    <SubTexture name="Mundo_04_Tile__0022_-" x="463" y="67" width="64" height="64"/>
    <SubTexture name="Mundo_04_Tile__0023_-" x="529" y="67" width="64" height="64"/>
    <SubTexture name="Mundo_04_Tile__0024_-" x="595" y="67" width="64" height="64"/>
    <SubTexture name="Mundo_04_Tile__0025_-" x="661" y="67" width="64" height="64"/>
    <SubTexture name="Mundo_04_Tile__0026_-" x="727" y="67" width="64" height="64"/>
    <SubTexture name="Mundo_04_Tile__0027_-" x="793" y="67" width="64" height="64"/>
    <SubTexture name="Mundo_04_Tile__0028_-" x="859" y="67" width="64" height="64"/>
    <SubTexture name="Mundo_04_Tile__0029_-" x="925" y="67" width="64" height="64"/>
    <SubTexture name="Mundo_04_Tile__0030_-" x="1" y="133" width="64" height="64"/>
    <SubTexture name="Mundo_04_Tile__0031_-" x="67" y="133" width="64" height="64"/>
    <SubTexture name="Mundo_04_Tile__0032_-" x="133" y="133" width="64" height="64"/>
    <SubTexture name="Mundo_04_Tile__0033_-" x="199" y="133" width="64" height="64"/>
    <SubTexture name="Mundo_04_Tile__0034_-" x="265" y="133" width="64" height="64"/>
    <SubTexture name="Mundo_04_Tile__0035_-" x="331" y="133" width="64" height="64"/>
    <SubTexture name="Mundo_04_Tile__0036_-" x="397" y="133" width="64" height="64"/>
    <SubTexture name="Mundo_04_Tile__0037_-" x="463" y="133" width="64" height="64"/>
    <SubTexture name="Mundo_04_Tile__0038_-" x="529" y="133" width="64" height="64"/>
    <SubTexture name="Mundo_04_Tile__0039_-" x="595" y="133" width="64" height="64"/>
    <SubTexture name="Mundo_04_Tile__0040_-" x="661" y="133" width="64" height="64"/>
    <SubTexture name="Mundo_04_Tile__0041_-" x="727" y="133" width="64" height="64"/>
    <SubTexture name="Mundo_04_Tile__0042_-" x="793" y="133" width="64" height="64"/>
    <SubTexture name="Mundo_04_Tile__0043_-" x="859" y="133" width="64" height="64"/>
    <SubTexture name="Mundo_04_Tile__0044_-" x="925" y="133" width="64" height="64"/>
    <SubTexture name="Mundo_04_Tile__0045_-" x="1" y="199" width="64" height="64"/>
    <SubTexture name="Mundo_04_Tile__0046_-" x="67" y="199" width="64" height="64"/>
    <SubTexture name="Mundo_04_Tile__0047_-" x="133" y="199" width="64" height="64"/>
    <SubTexture name="Mundo_04_Tile__0048_-" x="199" y="199" width="64" height="64"/>
    <SubTexture name="Mundo_04_Tile__0049_-" x="265" y="199" width="64" height="64"/>
    <SubTexture name="Mundo_04_Tile__0050_-" x="331" y="199" width="64" height="64"/>
    <SubTexture name="Mundo_04_Tile__0051_-" x="397" y="199" width="64" height="64"/>
    <SubTexture name="Mundo_04_Tile__0052_-" x="463" y="199" width="64" height="64"/>
    <SubTexture name="Mundo_04_Tile__0053_-" x="529" y="199" width="64" height="64"/>
    <SubTexture name="Mundo_04_Tile__0054_-" x="595" y="199" width="64" height="64"/>
    <SubTexture name="Mundo_04_Tile__0055_-" x="661" y="199" width="64" height="64"/>
    <SubTexture name="Mundo_04_Tile__0056_-" x="727" y="199" width="64" height="64"/>
    <SubTexture name="Mundo_04_Tile__0057_-" x="793" y="199" width="64" height="64"/>
    <SubTexture name="Mundo_04_Tile__0058_-" x="859" y="199" width="64" height="64"/>
    <SubTexture name="Mundo_04_Tile__0059_-" x="925" y="199" width="64" height="64"/>
    <SubTexture name="Mundo_04_Tile__0060_-" x="1" y="265" width="64" height="64"/>
    <SubTexture name="Mundo_04_Tile__0061_-" x="67" y="265" width="64" height="64"/>
    <SubTexture name="Mundo_04_Tile__0062_-" x="133" y="265" width="64" height="64"/>
    <SubTexture name="Mundo_04_Tile__0063_-" x="199" y="265" width="64" height="64"/>
    <SubTexture name="Mundo_04_Tile__0064_-" x="265" y="265" width="64" height="64"/>
    <SubTexture name="Mundo_04_Tile__0065_-" x="331" y="265" width="64" height="64"/>
    <SubTexture name="Mundo_04_Tile__0066_-" x="397" y="265" width="64" height="64"/>
    <SubTexture name="Mundo_04_Tile__0067_-" x="463" y="265" width="64" height="64"/>
    <SubTexture name="Mundo_04_Tile__0068_-" x="529" y="265" width="64" height="64"/>
    <SubTexture name="Mundo_04_Tile__0069_-" x="595" y="265" width="64" height="64"/>
    <SubTexture name="Mundo_04_Tile__0070_-" x="661" y="265" width="64" height="64"/>
    <SubTexture name="Mundo_04_Tile__0071_-" x="727" y="265" width="64" height="64"/>
    <SubTexture name="Mundo_04_Tile__0072_-" x="793" y="265" width="64" height="64"/>
    <SubTexture name="Mundo_04_Tile__0073_-" x="859" y="265" width="64" height="64"/>
    <SubTexture name="Mundo_04_Tile__0074_-" x="925" y="265" width="64" height="64"/>
    <SubTexture name="Mundo_04_Tile__0075_-" x="1" y="331" width="64" height="64"/>
    <SubTexture name="Mundo_04_Tile__0076_-" x="67" y="331" width="64" height="64"/>
    <SubTexture name="Mundo_04_Tile__0077_-" x="133" y="331" width="64" height="64"/>
    <SubTexture name="Mundo_04_Tile__0078_-" x="199" y="331" width="64" height="64"/>
    <SubTexture name="Mundo_04_Tile__0079_-" x="265" y="331" width="64" height="64"/>
    <SubTexture name="Mundo_04_Tile__0080_-" x="331" y="331" width="64" height="64"/>
    <SubTexture name="Mundo_04_Tile__0081_-" x="397" y="331" width="64" height="64"/>
    <SubTexture name="Mundo_04_Tile__0082_-" x="463" y="331" width="64" height="64"/>
    <SubTexture name="Mundo_04_Tile__0083_-" x="529" y="331" width="64" height="64"/>
    <SubTexture name="Mundo_04_Tile__0084_-" x="595" y="331" width="64" height="64"/>
    <SubTexture name="Mundo_04_Tile__0085_-" x="661" y="331" width="64" height="64"/>
    <SubTexture name="Mundo_04_Tile__0086_-" x="727" y="331" width="64" height="64"/>
    <SubTexture name="Mundo_04_Tile__0087_-" x="793" y="331" width="64" height="64"/>
    <SubTexture name="Mundo_04_Tile__0088_-" x="859" y="331" width="64" height="64"/>
    <SubTexture name="Mundo_04_Tile__0089_-" x="925" y="331" width="64" height="64"/>
    <SubTexture name="Mundo_04_Tile__0090_-" x="1" y="397" width="64" height="64"/>
    <SubTexture name="Mundo_04_Tile__0091_-" x="67" y="397" width="64" height="64"/>
    <SubTexture name="Mundo_04_Tile__0092_-" x="133" y="397" width="64" height="64"/>
    <SubTexture name="Mundo_04_Tile__0093_-" x="199" y="397" width="64" height="64"/>
    <SubTexture name="Mundo_04_Tile__0094_-" x="265" y="397" width="64" height="64"/>
    <SubTexture name="Mundo_04_Tile__0095_-" x="331" y="397" width="64" height="64"/>
    <SubTexture name="Mundo_04_Tile__0096_-" x="397" y="397" width="64" height="64"/>
    <SubTexture name="Mundo_04_Tile__0097_-" x="463" y="397" width="64" height="64"/>
    <SubTexture name="Mundo_04_Tile__0098_-" x="529" y="397" width="64" height="64"/>
    <SubTexture name="Mundo_04_Tile__0099_-" x="595" y="397" width="64" height="64"/>
    <SubTexture name="Mundo_04_Tile__0100_-" x="661" y="397" width="64" height="64"/>
    <SubTexture name="Mundo_04_Tile__0101_-" x="727" y="397" width="64" height="64"/>
    <SubTexture name="Mundo_04_Tile__0102_-" x="793" y="397" width="64" height="64"/>
    <SubTexture name="Mundo_04_Tile__0103_-" x="859" y="397" width="64" height="64"/>
    <SubTexture name="Mundo_04_Tile__0104_-" x="925" y="397" width="64" height="64"/>
    <SubTexture name="Mundo_04_Tile__0105_-" x="1" y="463" width="64" height="64"/>
    <SubTexture name="Mundo_04_Tile__0106_-" x="67" y="463" width="64" height="64"/>
    <SubTexture name="Mundo_04_Tile__0107_-" x="133" y="463" width="64" height="64"/>
    <SubTexture name="Mundo_04_Tile__0108_-" x="199" y="463" width="64" height="64"/>
    <SubTexture name="Mundo_04_Tile__0109_-" x="265" y="463" width="64" height="64"/>
    <SubTexture name="Mundo_04_Tile__0110_-" x="331" y="463" width="64" height="64"/>
    <SubTexture name="Mundo_04_Tile__0111_-" x="397" y="463" width="64" height="64"/>
    <SubTexture name="Mundo_04_Tile__0112_-" x="463" y="463" width="64" height="64"/>
    <SubTexture name="Mundo_04_Tile__0113_-" x="529" y="463" width="64" height="64"/>
    <SubTexture name="Mundo_04_Tile__0114_-" x="595" y="463" width="64" height="64"/>
    <SubTexture name="Mundo_04_Tile__0115_-" x="661" y="463" width="64" height="64"/>
    <SubTexture name="Mundo_04_Tile__0116_-" x="727" y="463" width="64" height="64"/>
    <SubTexture name="Mundo_04_Tile__0117_-" x="793" y="463" width="64" height="64"/>
    <SubTexture name="Mundo_04_Tile__0118_-" x="859" y="463" width="64" height="64"/>
    <SubTexture name="Mundo_04_Tile__0119_-" x="925" y="463" width="64" height="64"/>
    <SubTexture name="Mundo_04_Tile__0120_-" x="1" y="529" width="64" height="64"/>
    <SubTexture name="Mundo_04_Tile__0121_-" x="67" y="529" width="64" height="64"/>
    <SubTexture name="Mundo_04_Tile__0122_-" x="133" y="529" width="64" height="64"/>
    <SubTexture name="Mundo_04_Tile__0123_-" x="199" y="529" width="64" height="64"/>
    <SubTexture name="Mundo_04_Tile__0124_-" x="265" y="529" width="64" height="64"/>
    <SubTexture name="Mundo_04_Tile__0125_-" x="331" y="529" width="64" height="64"/>
    <SubTexture name="Mundo_04_Tile__0126_-" x="397" y="529" width="64" height="64"/>
    <SubTexture name="Mundo_04_Tile__0127_-" x="463" y="529" width="64" height="64"/>
    <SubTexture name="Mundo_04_Tile__0128_-" x="529" y="529" width="64" height="64"/>
    <SubTexture name="Mundo_04_Tile__0129_-" x="595" y="529" width="64" height="64"/>
    <SubTexture name="Mundo_04_Tile__0130_-" x="661" y="529" width="64" height="64"/>
    <SubTexture name="Mundo_04_Tile__0131_-" x="727" y="529" width="64" height="64"/>
    <SubTexture name="Mundo_04_Tile__0132_-" x="793" y="529" width="64" height="64"/>
    <SubTexture name="Mundo_04_Tile__0133_-" x="859" y="529" width="64" height="64"/>
    <SubTexture name="Mundo_04_Tile__0134_-" x="925" y="529" width="64" height="64"/>
    <SubTexture name="Mundo_04_Tile__0135_-" x="1" y="595" width="64" height="64"/>
    <SubTexture name="Mundo_04_Tile__0136_-" x="67" y="595" width="64" height="64"/>
    <SubTexture name="Mundo_04_Tile__0137_-" x="133" y="595" width="64" height="64"/>
    <SubTexture name="Mundo_04_Tile__0138_-" x="199" y="595" width="64" height="64"/>
    <SubTexture name="Mundo_04_Tile__0139_-" x="265" y="595" width="64" height="64"/>
    <SubTexture name="Mundo_04_Tile__0140_-" x="331" y="595" width="64" height="64"/>
    <SubTexture name="Mundo_04_Tile__0141_-" x="397" y="595" width="64" height="64"/>
    <SubTexture name="Mundo_04_Tile__0142_-" x="463" y="595" width="64" height="64"/>
    <SubTexture name="Mundo_04_Tile__0143_-" x="529" y="595" width="64" height="64"/>
    <SubTexture name="Mundo_04_Tile__0144_-" x="595" y="595" width="64" height="64"/>
    <SubTexture name="Mundo_04_Tile__0145_-" x="661" y="595" width="64" height="64"/>
    <SubTexture name="Mundo_04_Tile__0146_-" x="727" y="595" width="64" height="64"/>
    <SubTexture name="Mundo_04_Tile__0147_-" x="793" y="595" width="64" height="64"/>
    <SubTexture name="Mundo_04_Tile__0148_-" x="859" y="595" width="64" height="64"/>
    <SubTexture name="Mundo_04_Tile__0149_-" x="925" y="595" width="64" height="64"/>
    <SubTexture name="Mundo_04_Tile__0150_-" x="1" y="661" width="64" height="64"/>
    <SubTexture name="Mundo_04_Tile__0151_-" x="67" y="661" width="64" height="64"/>
    <SubTexture name="Mundo_04_Tile__0152_-" x="133" y="661" width="64" height="64"/>
    <SubTexture name="Mundo_04_Tile__0153_-" x="199" y="661" width="64" height="64"/>
    <SubTexture name="Mundo_04_Tile__0154_-" x="265" y="661" width="64" height="64"/>
    <SubTexture name="Mundo_04_Tile__0155_-" x="331" y="661" width="64" height="64"/>
    <SubTexture name="Mundo_04_Tile__0156_-" x="397" y="661" width="64" height="64"/>
    <SubTexture name="Mundo_04_Tile__0157_-" x="463" y="661" width="64" height="64"/>
    <SubTexture name="Mundo_04_Tile__0158_-" x="529" y="661" width="64" height="64"/>
    <SubTexture name="Mundo_04_Tile__0159_-" x="595" y="661" width="64" height="64"/>
    <SubTexture name="Mundo_04_Tile__0160_-" x="661" y="661" width="64" height="64"/>
    <SubTexture name="Mundo_04_Tile__0161_-" x="727" y="661" width="64" height="64"/>
    <SubTexture name="Mundo_04_Tile__0162_-" x="793" y="661" width="64" height="64"/>
    <SubTexture name="Mundo_04_Tile__0163_-" x="859" y="661" width="64" height="64"/>
    <SubTexture name="Mundo_04_Tile__0164_-" x="925" y="661" width="64" height="64"/>
    <SubTexture name="Mundo_04_Tile__0165_-" x="1" y="727" width="64" height="64"/>
    <SubTexture name="Mundo_04_Tile__0166_-" x="67" y="727" width="64" height="64"/>
    <SubTexture name="Mundo_04_Tile__0167_-" x="133" y="727" width="64" height="64"/>
    <SubTexture name="Mundo_04_Tile__0168_-" x="199" y="727" width="64" height="64"/>
    <SubTexture name="Mundo_04_Tile__0169_-" x="265" y="727" width="64" height="64"/>
    <SubTexture name="Mundo_04_Tile__0170_-" x="331" y="727" width="64" height="64"/>
    <SubTexture name="Mundo_04_Tile__0171_-" x="397" y="727" width="64" height="64"/>
    <SubTexture name="Mundo_04_Tile__0172_-" x="463" y="727" width="64" height="64"/>
    <SubTexture name="Mundo_04_Tile__0173_-" x="529" y="727" width="64" height="64"/>
    <SubTexture name="Mundo_04_Tile__0174_-" x="595" y="727" width="64" height="64"/>
    <SubTexture name="Mundo_04_Tile__0175_-" x="661" y="727" width="64" height="64"/>
    <SubTexture name="Mundo_04_Tile__0176_-" x="727" y="727" width="64" height="64"/>
    <SubTexture name="Mundo_04_Tile__0177_-" x="793" y="727" width="64" height="64"/>
    <SubTexture name="Mundo_04_Tile__0178_-" x="859" y="727" width="64" height="64"/>
    <SubTexture name="Mundo_04_Tile__0179_-" x="925" y="727" width="64" height="64"/>
    <SubTexture name="Mundo_04_Tile__0180_-" x="1" y="793" width="64" height="64"/>
    <SubTexture name="Mundo_04_Tile__0181_-" x="67" y="793" width="64" height="64"/>
    <SubTexture name="Mundo_04_Tile__0182_-" x="133" y="793" width="64" height="64"/>
    <SubTexture name="Mundo_04_Tile__0183_-" x="199" y="793" width="64" height="64"/>
    <SubTexture name="Mundo_04_Tile__0184_-" x="265" y="793" width="64" height="64"/>
    <SubTexture name="Mundo_04_Tile__0185_-" x="331" y="793" width="64" height="64"/>
    <SubTexture name="Mundo_04_Tile__0186_-" x="397" y="793" width="64" height="64"/>
    <SubTexture name="Mundo_04_Tile__0187_-" x="463" y="793" width="64" height="64"/>
    <SubTexture name="Mundo_04_Tile__0188_-" x="529" y="793" width="64" height="64"/>
    <SubTexture name="Mundo_04_Tile__0189_-" x="595" y="793" width="64" height="64"/>
    <SubTexture name="Mundo_04_Tile__0190_-" x="661" y="793" width="64" height="64"/>
    <SubTexture name="Mundo_04_Tile__0191_-" x="727" y="793" width="64" height="64"/>
    <SubTexture name="Mundo_04_Tile__0192_-" x="793" y="793" width="64" height="64"/>
    <SubTexture name="Mundo_04_Tile__0193_-" x="859" y="793" width="64" height="64"/>
    <SubTexture name="Mundo_04_Tile__0194_-" x="925" y="793" width="64" height="64"/>
    <SubTexture name="Mundo_04_Tile__0195_-" x="1" y="859" width="64" height="64"/>
    <SubTexture name="Mundo_04_Tile__0196_-" x="67" y="859" width="64" height="64"/>
    <SubTexture name="Mundo_04_Tile__0197_-" x="133" y="859" width="64" height="64"/>
    <SubTexture name="Mundo_04_Tile__0198_-" x="199" y="859" width="64" height="64"/>
    <SubTexture name="Mundo_04_Tile__0199_-" x="265" y="859" width="64" height="64"/>
    <SubTexture name="Mundo_04_Tile__0200_-" x="331" y="859" width="64" height="64"/>
    <SubTexture name="Mundo_04_Tile__0201_-" x="397" y="859" width="64" height="64"/>
    <SubTexture name="Mundo_04_Tile__0202_-" x="463" y="859" width="64" height="64"/>
    <SubTexture name="Mundo_04_Tile__0203_-" x="529" y="859" width="64" height="64"/>
    <SubTexture name="Mundo_04_Tile__0204_-" x="595" y="859" width="64" height="64"/>
    <SubTexture name="Mundo_04_Tile__0205_-" x="661" y="859" width="64" height="64"/>
    <SubTexture name="Mundo_04_Tile__0206_-" x="727" y="859" width="64" height="64"/>
    <SubTexture name="Mundo_04_Tile__0207_-" x="793" y="859" width="64" height="64"/>
    <SubTexture name="Mundo_04_Tile__0208_-" x="859" y="859" width="64" height="64"/>
    <SubTexture name="Mundo_04_Tile__0209_-" x="925" y="859" width="64" height="64"/>
    <SubTexture name="Mundo_04_Tile__0210_-" x="1" y="925" width="64" height="64"/>
    <SubTexture name="Mundo_04_Tile__0211_-" x="67" y="925" width="64" height="64"/>
    <SubTexture name="Mundo_04_Tile__0212_-" x="133" y="925" width="64" height="64"/>
    <SubTexture name="Mundo_04_Tile__0213_-" x="199" y="925" width="64" height="64"/>
    <SubTexture name="Mundo_04_Tile__0214_-" x="265" y="925" width="64" height="64"/>
    <SubTexture name="Mundo_04_Tile__0215_-" x="331" y="925" width="64" height="64"/>
    <SubTexture name="Mundo_04_Tile__0216_-" x="397" y="925" width="64" height="64"/>
    <SubTexture name="Mundo_04_Tile__0217_-" x="463" y="925" width="64" height="64"/>
    <SubTexture name="Mundo_04_Tile__0218_-" x="529" y="925" width="64" height="64"/>
    <SubTexture name="Mundo_04_Tile__0219_-" x="595" y="925" width="64" height="64"/>
    <SubTexture name="Mundo_04_Tile__0220_-" x="661" y="925" width="64" height="64"/>
    <SubTexture name="Mundo_04_Tile__0221_-" x="727" y="925" width="64" height="64"/>
    <SubTexture name="Mundo_04_Tile__0222_-" x="793" y="925" width="64" height="64"/>
    <SubTexture name="Mundo_04_Tile__0223_-" x="859" y="925" width="64" height="64"/>
    <SubTexture name="Mundo_04_Tile__0224_-" x="925" y="925" width="64" height="64"/>
    <SubTexture name="Mundo_04_Tile__0225_-" x="1" y="991" width="64" height="64"/>
    <SubTexture name="Mundo_04_Tile__0226_-" x="67" y="991" width="64" height="64"/>
    <SubTexture name="Mundo_04_Tile__0227_-" x="133" y="991" width="64" height="64"/>
    <SubTexture name="Mundo_04_Tile__0228_-" x="199" y="991" width="64" height="64"/>
    <SubTexture name="Mundo_04_Tile__0229_-" x="265" y="991" width="64" height="64"/>
    <SubTexture name="Mundo_04_Tile__0230_-" x="331" y="991" width="64" height="64"/>
    <SubTexture name="Mundo_04_Tile__0231_-" x="397" y="991" width="64" height="64"/>
    <SubTexture name="Mundo_04_Tile__0232_-" x="463" y="991" width="64" height="64"/>
    <SubTexture name="Mundo_04_Tile__0233_-" x="529" y="991" width="64" height="64"/>
    <SubTexture name="Mundo_04_Tile__0234_-" x="595" y="991" width="64" height="64"/>
    <SubTexture name="Mundo_04_Tile__0235_-" x="661" y="991" width="64" height="64"/>
    <SubTexture name="Mundo_04_Tile__0236_-" x="727" y="991" width="64" height="64"/>
    <SubTexture name="Mundo_04_Tile__0237_-" x="793" y="991" width="64" height="64"/>
    <SubTexture name="Mundo_04_Tile__0238_-" x="859" y="991" width="64" height="64"/>
    <SubTexture name="Mundo_04_Tile__0239_-" x="925" y="991" width="64" height="64"/>
    <SubTexture name="Mundo_04_Tile__0240_-" x="1" y="1057" width="64" height="64"/>
    <SubTexture name="Mundo_04_Tile__0241_-" x="67" y="1057" width="64" height="64"/>
</TextureAtlas>
